stemquests/__init__.py
stemquests/check_tor.py
stemquests/tor_instance.py
stemquests-1.1.1.dist-info/LICENSE
stemquests-1.1.1.dist-info/METADATA
stemquests-1.1.1.dist-info/WHEEL
stemquests-1.1.1.dist-info/top_level.txt
stemquests-1.1.1.dist-info/RECORD
