Metadata-Version: 2.1
Name: stemquests
Version: 1.1.1
Summary: Dark web HTTP requests using Tor, a stem helper library.
Author-email: Ian Costa <costa.ian18@gmail.com>
License: MIT License        
Project-URL: Homepage, https://github.com/SammyTheBEAST/stemquests
Project-URL: Bug Tracker, https://github.com/SammyTheBEAST/stemquests/issues
Keywords: tor,requests,stem,dark web
Classifier: License :: OSI Approved :: MIT License
Classifier: Programming Language :: Python
Classifier: Programming Language :: Python :: 3
Classifier: Topic :: Internet :: WWW/HTTP :: Session
Requires-Python: >=3.10
License-File: LICENSE
Requires-Dist: requests[socks]
Requires-Dist: stem
Requires-Dist: psutil
Provides-Extra: dev
Requires-Dist: pylint ; extra == 'dev'
Requires-Dist: autopep8 ; extra == 'dev'
Requires-Dist: isort ; extra == 'dev'
Requires-Dist: pytest ; extra == 'dev'
Requires-Dist: pip-tools ; extra == 'dev'
Requires-Dist: build ; extra == 'dev'
Requires-Dist: twine ; extra == 'dev'
